sysxtract/__init__.py
sysxtract/cli.py
sysxtract/sysmon.py
sysxtract/ui.py
sysxtract-1.0.0.dist-info/LICENSE
sysxtract-1.0.0.dist-info/METADATA
sysxtract-1.0.0.dist-info/WHEEL
sysxtract-1.0.0.dist-info/entry_points.txt
sysxtract-1.0.0.dist-info/top_level.txt
sysxtract-1.0.0.dist-info/RECORD
