Metadata-Version: 2.1
Name: sysxtract
Version: 1.0.0
Summary: Extract logs based off events from sysmon. Comes as a package, cli and ui.
Home-page: https://github.com/Ashton-Sidhu/sysmon-extract
Author: Ashton Sidhu
Author-email: sidhuashton@gmail.com
License: MIT
Keywords: datascience,security,infosec,analysis,pyspark,bigdata
Platform: UNKNOWN
Classifier: Programming Language :: Python :: 3.6
Classifier: Programming Language :: Python :: 3.7
Requires-Python: >= 3.6
Requires-Dist: click
Requires-Dist: openhunt
Requires-Dist: streamlit
Requires-Dist: pandas
